mock_spotfire/_core/__init__.py
mock_spotfire/_core/models.py
mock_spotfire/_core/paths.py
mock_spotfire/_core/router.py
mock_spotfire/_core/routes.py
mock_spotfire/automation_services_v1/__init__.py
mock_spotfire/automation_services_v1/errors.py
mock_spotfire/automation_services_v1/models.py
mock_spotfire/automation_services_v1/paths.py
mock_spotfire/automation_services_v1/state.py
mock_spotfire/automation_services_v1/routes/__init__.py
mock_spotfire/automation_services_v1/routes/abort.py
mock_spotfire/automation_services_v1/routes/start_library.py
mock_spotfire/automation_services_v1/routes/start_xml.py
mock_spotfire/automation_services_v1/routes/status.py
mock_spotfire/automation_services_v1/routes/test_hooks.py
mock_spotfire/library_v2/__init__.py
mock_spotfire/library_v2/errors.py
mock_spotfire/library_v2/models.py
mock_spotfire/library_v2/paths.py
mock_spotfire/library_v2/state.py
mock_spotfire/library_v2/routes/__init__.py
mock_spotfire/library_v2/routes/items.py
mock_spotfire/library_v2/routes/upload.py
spotfire_community/__init__.py
spotfire_community/py.typed
spotfire_community/_core/__init__.py
spotfire_community/_core/rest/__init__.py
spotfire_community/_core/rest/auth.py
spotfire_community/_core/rest/models.py
spotfire_community/_core/rest/spotfire_requests.py
spotfire_community/_core/validation/__init__.py
spotfire_community/_core/validation/uuid.py
spotfire_community/automation_services/__init__.py
spotfire_community/automation_services/client.py
spotfire_community/automation_services/errors.py
spotfire_community/automation_services/models.py
spotfire_community/automation_services/_xml/__init__.py
spotfire_community/automation_services/_xml/job_definition.py
spotfire_community/automation_services/_xml/tasks/__init__.py
spotfire_community/automation_services/_xml/tasks/apply_bookmark.py
spotfire_community/automation_services/_xml/tasks/open_analysis.py
spotfire_community/automation_services/_xml/tasks/task.py
spotfire_community/dxp/__init__.py
spotfire_community-0.4.1.dist-info/licenses/LICENSE
spotfire_community-0.4.1.dist-info/METADATA
spotfire_community-0.4.1.dist-info/WHEEL
spotfire_community-0.4.1.dist-info/top_level.txt
spotfire_community-0.4.1.dist-info/RECORD
