Metadata-Version: 2.4
Name: spotfire-community
Version: 0.4.1
Summary: Spotfire Community tools for working with the Spotfire Library API and DXP files.
Author-email: Clay Rankin <clay@wiserocksoftware.com>
License-Expression: MIT
Project-URL: Repository, https://github.com/scrankin/spotfire-community
Keywords: spotfire,dxp,rest,library,tibco
Classifier: Development Status :: 3 - Alpha
Classifier: Programming Language :: Python :: 3
Classifier: Programming Language :: Python :: 3.10
Classifier: Programming Language :: Python :: 3.11
Classifier: Programming Language :: Python :: 3.12
Classifier: Programming Language :: Python :: 3.13
Classifier: Typing :: Typed
Requires-Python: >=3.10
License-File: LICENSE
Requires-Dist: pydantic>=2.11.7
Requires-Dist: requests>=2.32.5
Dynamic: license-file
